neo_attachment/__init__.py
neo_attachment/config.py
neo_attachment/dependencies.py
neo_attachment/models.py
neo_attachment/routers.py
neo_attachment/schemas.py
neo_attachment/service.py
neo_attachment/setup.py
neo_attachment-0.0.1.dist-info/licenses/LICENSE
neo_attachment-0.0.1.dist-info/METADATA
neo_attachment-0.0.1.dist-info/WHEEL
neo_attachment-0.0.1.dist-info/RECORD
