Metadata-Version: 2.4
Name: neo-attachment
Version: 0.0.1
Summary: Attachment APIS for neoxin
License: MIT
License-File: LICENSE
Author: amiko
Author-email: haifei.cai@gientech.com
Requires-Python: >=3.13
Classifier: License :: OSI Approved :: MIT License
Classifier: Programming Language :: Python :: 3
Classifier: Programming Language :: Python :: 3.13
Classifier: Programming Language :: Python :: 3.14
Requires-Dist: neoxin-core (>=0.0.1,<0.1.0)
